[
  {
    "bvid": "BV1bkm6YWExG",
    "title": "空余时间也在练考核｜和博文一起跳舞｜被调侃像打工人｜张函瑞台历拍摄花絮单人cut",
    "cover": "http://i2.hdslb.com/bfs/archive/b583a4cd7b4654bff88031913c41d05d90b8633d.jpg",
    "url": "https://www.bilibili.com/video/BV1bkm6YWExG/",
    "date": "2024-11",
    "tags": [
      "考核"
    ]
  },
  {
    "bvid": "BV1DkDbYeE47",
    "title": "“要自信，没有信心什么都干不好”是一直鼓励夸赞队友的小队长呀｜张函瑞十月考核采访（下）",
    "cover": "http://i1.hdslb.com/bfs/archive/144e9eff4d73d4a849f9b9fddb8f6ff9b0252a1f.jpg",
    "url": "https://www.bilibili.com/video/BV1DkDbYeE47/",
    "date": "2024-11",
    "tags": [
      "考核"
    ]
  },
  {
    "bvid": "BV12nDWY5Eyt",
    "title": "通过话语感受到你的真心｜张函瑞10月考核采访（上）",
    "cover": "http://i2.hdslb.com/bfs/archive/bf5b97cea9dd576cabbe25c8ec4198ef3ae6acd9.jpg",
    "url": "https://www.bilibili.com/video/BV12nDWY5Eyt/",
    "date": "2024-11",
    "tags": [
      "考核"
    ]
  },
  {
    "bvid": "BV15yDWYZEUX",
    "title": "【张函瑞】弹唱考核 《阳光下的星星》好温柔好好听",
    "cover": "http://i0.hdslb.com/bfs/archive/5d4ebbb563d57075b69c26084569303aa3fe4f7a.jpg",
    "url": "https://www.bilibili.com/video/BV15yDWYZEUX/",
    "date": "2024-11",
    "tags": [
      "考核"
    ]
  },
  {
    "bvid": "BV1EEDsYvEt3",
    "title": "要的就是这股狠劲！！十月舞蹈考核张函瑞翻跳威神V《phantom》",
    "cover": "http://i1.hdslb.com/bfs/archive/accb1fd2f6c2b0e38d022f6bc241e8b5a391a186.jpg",
    "url": "https://www.bilibili.com/video/BV1EEDsYvEt3/",
    "date": "2024-11",
    "tags": [
      "考核"
    ]
  },
  {
    "bvid": "BV1SZbDz2EwU",
    "title": "哪里来的活力猫猫？！张函瑞《卡拉永远OK》考核",
    "cover": "http://i1.hdslb.com/bfs/archive/4bedf2631bd66f515d0e8aa403e78410f1906997.jpg",
    "url": "https://www.bilibili.com/video/BV1SZbDz2EwU/",
    "date": "2025-07",
    "tags": [
      "考核"
    ]
  },
  {
    "bvid": "BV1YDuQzkEDN",
    "title": "张函瑞《Go in blind》练习➕考核记录",
    "cover": "http://i2.hdslb.com/bfs/archive/9797bd161596b8ed05ac378e506b4f50e7e0aadb.jpg",
    "url": "https://www.bilibili.com/video/BV1YDuQzkEDN/",
    "date": "2025-07",
    "tags": [
      "考核"
    ]
  },
  {
    "bvid": "BV1TktpzcEcE",
    "title": "个人觉得全场最佳！！第二组《路灯下的小姑娘》考核｜有大主唱和声就是强",
    "cover": "http://i1.hdslb.com/bfs/archive/f1280d828f96cc8964940166e62be08ff5d8c002.jpg",
    "url": "https://www.bilibili.com/video/BV1TktpzcEcE/",
    "date": "2025-08",
    "tags": [
      "考核"
    ]
  },
  {
    "bvid": "BV11Mtmz8Evn",
    "title": "完全碾压级别的好听！！张函瑞《暮色回响》考核",
    "cover": "http://i1.hdslb.com/bfs/archive/7933907792410bca9edb7dd1b143950e0b29b64a.jpg",
    "url": "https://www.bilibili.com/video/BV11Mtmz8Evn/",
    "date": "2025-08",
    "tags": [
      "考核"
    ]
  },
  {
    "bvid": "BV186tmzBEaz",
    "title": "终于等到声乐考核！！张函瑞《雨爱》考核好听到哭",
    "cover": "http://i0.hdslb.com/bfs/archive/dc4b23403548f66cf1158b1fe07a4f528fcc427f.jpg",
    "url": "https://www.bilibili.com/video/BV186tmzBEaz/",
    "date": "2025-08",
    "tags": [
      "考核"
    ]
  },
  {
    "bvid": "BV1fphpz9ET2",
    "title": "状态起飞的纯舞考核！！表管好牛《Deja Vu》张函瑞考核cut",
    "cover": "http://i2.hdslb.com/bfs/archive/323f359b8d6dfb0c4c903ca30475179ebf2948b9.jpg",
    "url": "https://www.bilibili.com/video/BV1fphpz9ET2/",
    "date": "2025-08",
    "tags": [
      "考核"
    ]
  },
  {
    "bvid": "BV1LdWxz5Emo",
    "title": "【张函瑞】确定下次考核曲目是《言不由衷》难度比较大练习加油！",
    "cover": "http://i2.hdslb.com/bfs/archive/149ab1061a0aa83114535fa6d295cb22663daf54.jpg",
    "url": "https://www.bilibili.com/video/BV1LdWxz5Emo/",
    "date": "2025-10",
    "tags": [
      "考核"
    ]
  },
  {
    "bvid": "BV1Xk4wz1EAf",
    "title": "【张函瑞】如果选一首以前唱过的歌作为考核曲目…终于可以弥补遗憾了吗",
    "cover": "http://i2.hdslb.com/bfs/archive/d7400ed7fb7e24c7c4826697e3908535f4897ce9.jpg",
    "url": "https://www.bilibili.com/video/BV1Xk4wz1EAf/",
    "date": "2025-10",
    "tags": [
      "考核"
    ]
  },
  {
    "bvid": "BV1Mr4EzHEJX",
    "title": "【张函瑞十月考核】越来越强的舞蹈考核！！纯血主舞的魅力绽放时刻 ✧",
    "cover": "http://i1.hdslb.com/bfs/archive/be3abf1919b2d453059e00c6685208797a3e48b2.jpg",
    "url": "https://www.bilibili.com/video/BV1Mr4EzHEJX/",
    "date": "2025-10",
    "tags": [
      "考核"
    ]
  },
  {
    "bvid": "BV1Gcxtz2EXT",
    "title": "疑似考核曲目泄露？张函瑞声乐练习Tori kelly《Sorry Would Go a Long Way》",
    "cover": "http://i0.hdslb.com/bfs/archive/bf9c53316e1a8213d64cae6da312ce813d487aad.jpg",
    "url": "https://www.bilibili.com/video/BV1Gcxtz2EXT/",
    "date": "2025-10",
    "tags": [
      "考核"
    ]
  },
  {
    "bvid": "BV1DSSqB7Emr",
    "title": "用九分钟的采访看到你强大的内核力量｜张函瑞考核采访全程cut（声乐/舞蹈/乐队/团体舞/自我评价）",
    "cover": "http://i1.hdslb.com/bfs/archive/090123d7f4f7760f1ca0c4488239847d9f04846a.jpg",
    "url": "https://www.bilibili.com/video/BV1DSSqB7Emr/",
    "date": "2025-11",
    "tags": [
      "考核"
    ]
  },
  {
    "bvid": "BV1ukUfBzERv",
    "title": "【张函瑞】乐队考核《艾蜜莉》单人纯享版",
    "cover": "http://i1.hdslb.com/bfs/archive/d7340f6c248d44b9509de4cb33125e26abed9c40.jpg",
    "url": "https://www.bilibili.com/video/BV1ukUfBzERv/",
    "date": "2025-11",
    "tags": [
      "考核"
    ]
  },
  {
    "bvid": "BV1qgSFBJE9W",
    "title": "【张函瑞】团体舞考核《Problem With You》单人直拍｜这次真的是男神降临了…",
    "cover": "http://i2.hdslb.com/bfs/archive/2f2869e941a58a8ebde2d8e9df5ac0e0c892ccb1.jpg",
    "url": "https://www.bilibili.com/video/BV1qgSFBJE9W/",
    "date": "2025-11",
    "tags": [
      "考核"
    ]
  },
  {
    "bvid": "BV1kdUfBfEZU",
    "title": "乐队考核第二组《艾蜜莉》主唱开口定调｜夕阳掉进我心里~",
    "cover": "http://i2.hdslb.com/bfs/archive/f18366a92c01fa08daacb0028d7e888b90fedb29.jpg",
    "url": "https://www.bilibili.com/video/BV1kdUfBfEZU/",
    "date": "2025-11",
    "tags": [
      "考核"
    ]
  },
  {
    "bvid": "BV1BTSFBHEjz",
    "title": "很难想象这是纯血上楼的舞蹈实力…张函瑞舞蹈考核《Bombelelo (feat. Sie Konko)》大魔王来袭",
    "cover": "http://i1.hdslb.com/bfs/archive/b596fab126ed501c363681349104a9da0cb943c2.jpg",
    "url": "https://www.bilibili.com/video/BV1BTSFBHEjz/",
    "date": "2025-11",
    "tags": [
      "考核"
    ]
  },
  {
    "bvid": "BV1HvUWB4EsH",
    "title": "【张函瑞】舞蹈练习《Focus》终于等到女团舞考核了吗？！",
    "cover": "http://i0.hdslb.com/bfs/archive/36c60fcdc0e57e9939a70f6294214684e2e09266.jpg",
    "url": "https://www.bilibili.com/video/BV1HvUWB4EsH/",
    "date": "2025-11",
    "tags": [
      "考核"
    ]
  },
  {
    "bvid": "BV1niUWBdEsB",
    "title": "【张函瑞】到了每周的汇报时间~这次选的舞蹈难度比较大，期待最后的考核成果！！",
    "cover": "http://i2.hdslb.com/bfs/archive/37901b4633a9f255b52d25717208fbcbb20ed0ec.jpg",
    "url": "https://www.bilibili.com/video/BV1niUWBdEsB/",
    "date": "2025-11",
    "tags": [
      "考核"
    ]
  },
  {
    "bvid": "BV1zLCyBAEbu",
    "title": "张函瑞《言不由衷》声乐练习好好听！！考核期待值拉满",
    "cover": "http://i0.hdslb.com/bfs/archive/3670846a856445b07146d6eef2d0614de40edc7a.jpg",
    "url": "https://www.bilibili.com/video/BV1zLCyBAEbu/",
    "date": "2025-11",
    "tags": [
      "考核"
    ]
  },
  {
    "bvid": "BV1vc2EBtEnK",
    "title": "一个人的身体怎么能如此灵活？！张函瑞考核奖励舞台《Bombelelo (feat. Sie Konko)》",
    "cover": "http://i1.hdslb.com/bfs/archive/9ac7e4ac67c307290e9bef8b5de68b2246a5e23e.jpg",
    "url": "https://www.bilibili.com/video/BV1vc2EBtEnK/",
    "date": "2025-12",
    "tags": [
      "考核"
    ]
  },
  {
    "bvid": "BV1nU27BiEWA",
    "title": "【张函瑞】考核奖励舞台《言不由衷》误入凡间的妙音仙子",
    "cover": "http://i0.hdslb.com/bfs/archive/f5fc1051918c516652c95e6808804747a24bddf7.jpg",
    "url": "https://www.bilibili.com/video/BV1nU27BiEWA/",
    "date": "2025-12",
    "tags": [
      "考核"
    ]
  }
]