[
  {
    "bvid": "BV1vUSEBKEuM",
    "title": "【TF家族练习生】《星期五练习生》112:虚无游戏世界",
    "cover": "http://i2.hdslb.com/bfs/archive/fda0830dc9d2d407fea69863872a767b33cfdeb0.jpg",
    "url": "https://www.bilibili.com/video/BV1vUSEBKEuM/",
    "date": "2025-11"
  },
  {
    "bvid": "BV1xnmmBcEtr",
    "title": "【TF家族练习生】《星期五练习生》113:安静的美男子",
    "cover": "http://i2.hdslb.com/bfs/archive/4d83fb015e8e9ee5407c05357c3340b7680822bd.jpg",
    "url": "https://www.bilibili.com/video/BV1xnmmBcEtr/",
    "date": "2025-12"
  },
  {
    "bvid": "BV1BAq9B6Ej3",
    "title": "【TF家族练习生】《星期五练习生》114:今天不许好好唱",
    "cover": "http://i1.hdslb.com/bfs/archive/4d150183de5100500020e77b87b5bc8b0beba924.jpg",
    "url": "https://www.bilibili.com/video/BV1BAq9B6Ej3/",
    "date": "2025-12"
  },
  {
    "bvid": "BV1vtvQBZEf2",
    "title": "【TF家族练习生】《星期五练习生》115：我们的“元”气值满了",
    "cover": "http://i1.hdslb.com/bfs/archive/9b3dc3feb6d14590496fdfa3f82bc3af1c7fe3ad.jpg",
    "url": "https://www.bilibili.com/video/BV1vtvQBZEf2/",
    "date": "2026-01"
  },
  {
    "bvid": "BV1vPiFB7Eap",
    "title": "【TF家族练习生】《星期五练习生》116：神的主理人",
    "cover": "http://i0.hdslb.com/bfs/archive/727266af41aa9e91a2eb5cdde7c9d29793063318.jpg",
    "url": "https://www.bilibili.com/video/BV1vPiFB7Eap/",
    "date": "2026-01"
  },
  {
    "bvid": "BV1ztrKBXE6n",
    "title": "【TF家族练习生】《星期五练习生》117：直觉无限公司",
    "cover": "http://i1.hdslb.com/bfs/archive/3f56f9fdc2f1762f17428939479a47e811385d40.jpg",
    "url": "https://www.bilibili.com/video/BV1ztrKBXE6n/",
    "date": "2026-01"
  },
  {
    "bvid": "BV1dFrkBmEDt",
    "title": "【TF家族练习生】《星期五练习生》118：高雅人士局",
    "cover": "http://i0.hdslb.com/bfs/archive/e836d0958d279ab65b608165adead27f29388365.jpg",
    "url": "https://www.bilibili.com/video/BV1dFrkBmEDt/",
    "date": "2026-01"
  },
  {
    "bvid": "BV1hYzMBgEk5",
    "title": "【TF家族练习生】《星期五练习生》119：纸上谈兵",
    "cover": "http://i2.hdslb.com/bfs/archive/38c7361ee430a204e4e8dc2f2464b045f2f4bf45.jpg",
    "url": "https://www.bilibili.com/video/BV1hYzMBgEk5/",
    "date": "2026-01"
  },
  {
    "bvid": "BV1J36vBPEWr",
    "title": "【TF家族练习生】《星期五练习生》120：抽象的狼人杀",
    "cover": "http://i2.hdslb.com/bfs/archive/53c994b6b6549b5d4c327ae900701c91252846b6.jpg",
    "url": "https://www.bilibili.com/video/BV1J36vBPEWr/",
    "date": "2026-01"
  },
  {
    "bvid": "BV1VvZTBRELU",
    "title": "【TF家族练习生】《星期五练习生》122：《厨神争霸》",
    "cover": "http://i2.hdslb.com/bfs/archive/9894687d703b6974d01b94160cb230b0e8552212.jpg",
    "url": "https://www.bilibili.com/video/BV1VvZTBRELU/",
    "date": "2026-02"
  },
  {
    "bvid": "BV1TXZrB3Eux",
    "title": "【TF家族练习生】《星期五练习生》123：《反差的LOVE》",
    "cover": "http://i0.hdslb.com/bfs/archive/060f8f04a0bb1cc695a0c9e31396d261311f33a0.jpg",
    "url": "https://www.bilibili.com/video/BV1TXZrB3Eux/",
    "date": "2026-02"
  },
  {
    "bvid": "BV1xYsnzmEV3",
    "title": "【TF家族练习生】《星期五练习生》107:离谱马拉松大赛",
    "cover": "http://i2.hdslb.com/bfs/archive/67ddfc9df44a0a0a29b10b533f525be02a1d2d11.jpg",
    "url": "https://www.bilibili.com/video/BV1xYsnzmEV3/",
    "date": "2025-10"
  },
  {
    "bvid": "BV1os1KBbEoL",
    "title": "【TF家族练习生】《星期五练习生》108:“阿巴阿巴”描述大会",
    "cover": "http://i0.hdslb.com/bfs/archive/f5663d94f25501378422b419dc6b4efffa45ccbb.jpg",
    "url": "https://www.bilibili.com/video/BV1os1KBbEoL/",
    "date": "2025-10"
  },
  {
    "bvid": "BV1qP23BGEaw",
    "title": "【TF家族练习生】《星期五练习生》109:好想这样活一次",
    "cover": "http://i2.hdslb.com/bfs/archive/c7bcaf0ab0dd3c93e9906a883013910c1700eb6e.jpg",
    "url": "https://www.bilibili.com/video/BV1qP23BGEaw/",
    "date": "2025-11"
  },
  {
    "bvid": "BV1HACMBvETY",
    "title": "【TF家族练习生】《星期五练习生》110:鸭力不山大",
    "cover": "http://i1.hdslb.com/bfs/archive/eeb8152af26f954dfc1b21bfddfb5c9ae760cb17.jpg",
    "url": "https://www.bilibili.com/video/BV1HACMBvETY/",
    "date": "2025-11"
  },
  {
    "bvid": "BV11YUjByEr5",
    "title": "【TF家族练习生】《星期五练习生》111:你的尖叫我的梦",
    "cover": "http://i2.hdslb.com/bfs/archive/cb319d125d293e05ef5355a80e00d10596bbcab3.jpg",
    "url": "https://www.bilibili.com/video/BV11YUjByEr5/",
    "date": "2025-11"
  },
  {
    "bvid": "BV19hWCzWEJj",
    "title": "【TF家族练习生】《星期五练习生》106：“海龟”不是“这个汤”",
    "cover": "http://i0.hdslb.com/bfs/archive/30836e9bff6a353a31f83da3811671357ef026c1.jpg",
    "url": "https://www.bilibili.com/video/BV19hWCzWEJj/",
    "date": "2025-10"
  },
  {
    "bvid": "BV13b421E7Qu",
    "title": "【TF家族练习生】《星期五练习生》58:「修渔期」EP03——突如其来的食材寻宝",
    "cover": "http://i1.hdslb.com/bfs/archive/8c0d30e12f915359134ff48d1d7a48f4be852962.jpg",
    "url": "https://www.bilibili.com/video/BV13b421E7Qu/",
    "date": "2024-08"
  },
  {
    "bvid": "BV1BgHVzzEHm",
    "title": "【TF家族练习生】《星期五练习生》105：卡丁车接力赛",
    "cover": "http://i0.hdslb.com/bfs/archive/11f60140e2cfb6e3207fa5b1564ea6c35eb550dd.jpg",
    "url": "https://www.bilibili.com/video/BV1BgHVzzEHm/",
    "date": "2025-10"
  },
  {
    "bvid": "BV1mAnVznEnQ",
    "title": "【TF家族练习生】《星期五练习生》104：命运的巅峰对决",
    "cover": "http://i0.hdslb.com/bfs/archive/8699338d8ca99c605c7e8fcb2a6215b75b548f00.jpg",
    "url": "https://www.bilibili.com/video/BV1mAnVznEnQ/",
    "date": "2025-09"
  },
  {
    "bvid": "BV1UcW3zREpy",
    "title": "【TF家族练习生】《星期五练习生》103：人生就是冲刺",
    "cover": "http://i0.hdslb.com/bfs/archive/89f75001e0478a94bf966dcd0496290e543e5518.jpg",
    "url": "https://www.bilibili.com/video/BV1UcW3zREpy/",
    "date": "2025-09"
  },
  {
    "bvid": "BV167Hkz4ELh",
    "title": "【TF家族练习生】《星期五练习生》102：神奇的猜丁壳",
    "cover": "http://i0.hdslb.com/bfs/archive/014110698f64d0573937afabef0134726b172b39.jpg",
    "url": "https://www.bilibili.com/video/BV167Hkz4ELh/",
    "date": "2025-09"
  },
  {
    "bvid": "BV1HzTuzAEqC",
    "title": "【TF家族练习生】《星期五练习生》98：无间道",
    "cover": "http://i2.hdslb.com/bfs/archive/f74dd41c487f5b4f188556414c60aebcc6ad163c.jpg",
    "url": "https://www.bilibili.com/video/BV1HzTuzAEqC/",
    "date": "2025-06"
  },
  {
    "bvid": "BV1Y6EtzeEXo",
    "title": "【TF家族练习生】《星期五练习生》95：瞧我的小嘴巴",
    "cover": "http://i1.hdslb.com/bfs/archive/58b5eaabddb4606c80ef7332b5cc282f58880f51.jpg",
    "url": "https://www.bilibili.com/video/BV1Y6EtzeEXo/",
    "date": "2025-05"
  },
  {
    "bvid": "BV16WZ9YuEXi",
    "title": "【TF家族练习生】《星期五练习生》89：甜度爆表",
    "cover": "http://i2.hdslb.com/bfs/archive/bd85becf855c93731c0bc21c686dbb7bd12c2ee1.jpg",
    "url": "https://www.bilibili.com/video/BV16WZ9YuEXi/",
    "date": "2025-04"
  },
  {
    "bvid": "BV15RXkYDEyf",
    "title": "【TF家族练习生】《星期五练习生》86：热火朝天的冬季集训（4）",
    "cover": "http://i0.hdslb.com/bfs/archive/bb7b31214dcb636a508c20b1fc70aa3d19493ceb.jpg",
    "url": "https://www.bilibili.com/video/BV15RXkYDEyf/",
    "date": "2025-03"
  },
  {
    "bvid": "BV1uQQzYAE2z",
    "title": "【TF家族练习生】《星期五练习生》85：热火朝天的冬季集训（3）",
    "cover": "http://i1.hdslb.com/bfs/archive/8a47c712ea63cb2caed8b674f98b0684ee04b0f0.jpg",
    "url": "https://www.bilibili.com/video/BV1uQQzYAE2z/",
    "date": "2025-03"
  },
  {
    "bvid": "BV1cV91YgEiL",
    "title": "【TF家族练习生】《星期五练习生》84：热火朝天的冬季集训（2）",
    "cover": "http://i2.hdslb.com/bfs/archive/f54fe594e7afd8923bb91dd202b3a29381f469bf.jpg",
    "url": "https://www.bilibili.com/video/BV1cV91YgEiL/",
    "date": "2025-03"
  },
  {
    "bvid": "BV1Rp9uY4ExU",
    "title": "【TF家族练习生】《星期五练习生》83：热火朝天的冬季集训（1）",
    "cover": "http://i2.hdslb.com/bfs/archive/f61453580a17573a85319210069510e0849bdc10.jpg",
    "url": "https://www.bilibili.com/video/BV1Rp9uY4ExU/",
    "date": "2025-02"
  },
  {
    "bvid": "BV1hXAoeyETm",
    "title": "【TF家族练习生】《星期五练习生》82：谁是三寸不烂之舌",
    "cover": "http://i1.hdslb.com/bfs/archive/6e3e3de48e870e5ad3b0f9d47e4deff6b0115c2d.jpg",
    "url": "https://www.bilibili.com/video/BV1hXAoeyETm/",
    "date": "2025-02"
  },
  {
    "bvid": "BV1pJKjedEF2",
    "title": "【TF家族练习生】《星期五练习生》81：圆圆滚滚乐发财",
    "cover": "http://i0.hdslb.com/bfs/archive/84f91d0d3684aa2488d54b5ff35e14df5a35f75f.jpg",
    "url": "https://www.bilibili.com/video/BV1pJKjedEF2/",
    "date": "2025-02"
  },
  {
    "bvid": "BV1SDFoeNEgg",
    "title": "【TF家族练习生】《星期五练习生》80：我这无人能敌的手气",
    "cover": "http://i0.hdslb.com/bfs/archive/7e156db3d264e2f1ed50d55023fcbb01fb5096ed.jpg",
    "url": "https://www.bilibili.com/video/BV1SDFoeNEgg/",
    "date": "2025-02"
  },
  {
    "bvid": "BV1hefHYKEDF",
    "title": "【TF家族练习生】《星期五练习生》79：这个feel倍儿爽",
    "cover": "http://i1.hdslb.com/bfs/archive/32bc0c56a5855c8f17250d26ba5058b29d93e525.jpg",
    "url": "https://www.bilibili.com/video/BV1hefHYKEDF/",
    "date": "2025-01"
  },
  {
    "bvid": "BV1skCpYREdE",
    "title": "【TF家族练习生】《星期五练习生》78：距离的神",
    "cover": "http://i1.hdslb.com/bfs/archive/5c6a1e32b833a9fc25c9af8369da6974cf30eeee.jpg",
    "url": "https://www.bilibili.com/video/BV1skCpYREdE/",
    "date": "2024-12"
  },
  {
    "bvid": "BV1bJBLYfEJz",
    "title": "【TF家族练习生】《星期五练习生》76：新脑子转的就是快:",
    "cover": "http://i0.hdslb.com/bfs/archive/e8d2b211bcc377781c72d785f91f88ab8da6a450.jpg",
    "url": "https://www.bilibili.com/video/BV1bJBLYfEJz/",
    "date": "2024-12"
  },
  {
    "bvid": "BV1KMiBYUELc",
    "title": "【TF家族练习生】《星期五练习生》75：气吞山河之战",
    "cover": "http://i2.hdslb.com/bfs/archive/1e5a15b63db12e315673f1e545dab158c464e65a.jpg",
    "url": "https://www.bilibili.com/video/BV1KMiBYUELc/",
    "date": "2024-12"
  },
  {
    "bvid": "BV1fBBiYTE34",
    "title": "【TF家族练习生】《星期五练习生》73：jio痛的僵尸",
    "cover": "http://i2.hdslb.com/bfs/archive/78301a2c7320cde924a10a67081120969921a019.jpg",
    "url": "https://www.bilibili.com/video/BV1fBBiYTE34/",
    "date": "2024-11"
  },
  {
    "bvid": "BV1KTSRYhE8C",
    "title": "【TF家族练习生】《星期五练习生》70：mini秋季运动会",
    "cover": "http://i1.hdslb.com/bfs/archive/340c586047d51e21585b0762a3da3dd04bb0d385.jpg",
    "url": "https://www.bilibili.com/video/BV1KTSRYhE8C/",
    "date": "2024-11"
  },
  {
    "bvid": "BV1aNyDYmEyx",
    "title": "【TF家族练习生】《星期五练习生》69：怎么不算city walk呢",
    "cover": "http://i2.hdslb.com/bfs/archive/fe4a93d31fc272a58c21ce474e69193e3997bd51.jpg",
    "url": "https://www.bilibili.com/video/BV1aNyDYmEyx/",
    "date": "2024-10"
  },
  {
    "bvid": "BV17FC2YkEmc",
    "title": "【TF家族练习生】《星期五练习生》68：Kampai!",
    "cover": "http://i2.hdslb.com/bfs/archive/a5fdebaa7775e7bfeeb649b846379a964ac48650.jpg",
    "url": "https://www.bilibili.com/video/BV17FC2YkEmc/",
    "date": "2024-10"
  },
  {
    "bvid": "BV1UP2mYBEAo",
    "title": "【TF家族练习生】《星期五练习生》67：大快朵颐",
    "cover": "http://i2.hdslb.com/bfs/archive/a5fdebaa7775e7bfeeb649b846379a964ac48650.jpg",
    "url": "https://www.bilibili.com/video/BV1UP2mYBEAo/",
    "date": "2024-10"
  },
  {
    "bvid": "BV1dQ4FeHEVY",
    "title": "【TF家族练习生】《星期五练习生》66：忙忙碌碌寻宝藏",
    "cover": "http://i2.hdslb.com/bfs/archive/fe4a93d31fc272a58c21ce474e69193e3997bd51.jpg",
    "url": "https://www.bilibili.com/video/BV1dQ4FeHEVY/",
    "date": "2024-10"
  },
  {
    "bvid": "BV1VHxrecE7F",
    "title": "【TF家族练习生】《星期五练习生》65:「修渔期」花絮篇",
    "cover": "http://i2.hdslb.com/bfs/archive/88256b904b36e5d80ee6f4be148310f166c62c4a.jpg",
    "url": "https://www.bilibili.com/video/BV1VHxrecE7F/",
    "date": "2024-09"
  },
  {
    "bvid": "BV1WPxFehECF",
    "title": "【TF家族练习生】《星期五练习生》64:「修渔期」EP08——即刻回家",
    "cover": "http://i1.hdslb.com/bfs/archive/9e86cef394d28f9a1432f5536264a461dba38515.jpg",
    "url": "https://www.bilibili.com/video/BV1WPxFehECF/",
    "date": "2024-09"
  },
  {
    "bvid": "BV1iwtfe9EJu",
    "title": "【TF家族练习生】《星期五练习生》63:「修渔期」EP07—— 一日店长之意想不到的客人（下）",
    "cover": "http://i2.hdslb.com/bfs/archive/a4def3791a8acc38f314523bbab5aba75c021011.jpg",
    "url": "https://www.bilibili.com/video/BV1iwtfe9EJu/",
    "date": "2024-09"
  },
  {
    "bvid": "BV1hgteeGEzP",
    "title": "【TF家族练习生】《星期五练习生》62：中秋特辑",
    "cover": "http://i2.hdslb.com/bfs/archive/8a851693d3e43919d2a56231728fede1c9deea1f.jpg",
    "url": "https://www.bilibili.com/video/BV1hgteeGEzP/",
    "date": "2024-09"
  },
  {
    "bvid": "BV1BL4bezEXN",
    "title": "【TF家族练习生】《星期五练习生》61:「修渔期」EP06—— 一日店长之意想不到的客人",
    "cover": "http://i0.hdslb.com/bfs/archive/88e6fb7c62a48d418912ade8ef56e12d4c6179e3.jpg",
    "url": "https://www.bilibili.com/video/BV1BL4bezEXN/",
    "date": "2024-09"
  },
  {
    "bvid": "BV1eQH9eWEPG",
    "title": "【TF家族练习生】《星期五练习生》60:「修渔期」EP05——泥潭大作战",
    "cover": "http://i2.hdslb.com/bfs/archive/4164addbf1209d60dbaa074460d654b0ea596574.jpg",
    "url": "https://www.bilibili.com/video/BV1eQH9eWEPG/",
    "date": "2024-09"
  },
  {
    "bvid": "BV16E421c7hb",
    "title": "【TF家族练习生】《星期五练习生》59:「修渔期」EP04——渔业研修日",
    "cover": "http://i0.hdslb.com/bfs/archive/6aa17887b70bcdf34a8a3608203718af8b827a4a.jpg",
    "url": "https://www.bilibili.com/video/BV16E421c7hb/",
    "date": "2024-08"
  },
  {
    "bvid": "BV1dr421M7cD",
    "title": "【TF家族练习生】《星期五练习生》57:「修渔期」EP02——新地图探索度？%",
    "cover": "http://i1.hdslb.com/bfs/archive/9a18959370f9802cbd5231442fea7ce08e2a2869.jpg",
    "url": "https://www.bilibili.com/video/BV1dr421M7cD/",
    "date": "2024-08"
  },
  {
    "bvid": "BV1Ff421i7dA",
    "title": "【TF家族练习生】《星期五练习生》56:「修渔期」EP01——村里来了群中小学生",
    "cover": "http://i2.hdslb.com/bfs/archive/0c29ec727bd06e38f02d36355a18d16d93385a4f.jpg",
    "url": "https://www.bilibili.com/video/BV1Ff421i7dA/",
    "date": "2024-08"
  },
  {
    "bvid": "BV1j142187V2",
    "title": "【TF家族练习生】《星期五练习生》55:「修渔期」先导片——神级转场",
    "cover": "http://i2.hdslb.com/bfs/archive/8f9685e5aaab7904cf56b8532f45552a24f6f3c8.jpg",
    "url": "https://www.bilibili.com/video/BV1j142187V2/",
    "date": "2024-08"
  },
  {
    "bvid": "BV1W142187Np",
    "title": "【TF家族练习生】《星期五练习生》54：澳门！我们来啦！",
    "cover": "http://i1.hdslb.com/bfs/archive/1cdb92b2ce6fe9d11ba825fd037c6e97a204b5e2.jpg",
    "url": "https://www.bilibili.com/video/BV1W142187Np/",
    "date": "2024-07"
  },
  {
    "bvid": "BV12E4m1R7q5",
    "title": "【TF家族练习生】《星期五练习生》53：就问你服（福）不服（福）",
    "cover": "http://i1.hdslb.com/bfs/archive/aca7f96d85f0831ea54a933f971c1b5b8545c42d.jpg",
    "url": "https://www.bilibili.com/video/BV12E4m1R7q5/",
    "date": "2024-07"
  },
  {
    "bvid": "BV1im421G7mL",
    "title": "【TF家族练习生】《星期五练习生》52: 富翁囧囧囧",
    "cover": "http://i1.hdslb.com/bfs/archive/a3167b999d2f4d238a7602d2d796965f16bb6fda.jpg",
    "url": "https://www.bilibili.com/video/BV1im421G7mL/",
    "date": "2024-07"
  },
  {
    "bvid": "BV1k4421D7MK",
    "title": "【TF家族练习生】《星期五练习生》51: 穿越时空长廊（下）",
    "cover": "http://i0.hdslb.com/bfs/archive/a33f9e70420412c4d9930b10c93d8d9c9ba0e648.jpg",
    "url": "https://www.bilibili.com/video/BV1k4421D7MK/",
    "date": "2024-07"
  },
  {
    "bvid": "BV1jf421Q7W1",
    "title": "【TF家族练习生】《星期五练习生》50：穿越时空长廊（上）",
    "cover": "http://i1.hdslb.com/bfs/archive/ab2e472a9380fb93a7d97d0e48462d7d1225291c.jpg",
    "url": "https://www.bilibili.com/video/BV1jf421Q7W1/",
    "date": "2024-06"
  },
  {
    "bvid": "BV1Jf421Q7Tz",
    "title": "【TF家族练习生】《星期五练习生》49：燃烧的团结之魂",
    "cover": "http://i2.hdslb.com/bfs/archive/541841bfd62b0eb6a91bab643b54b993dbaf297c.jpg",
    "url": "https://www.bilibili.com/video/BV1Jf421Q7Tz/",
    "date": "2024-06"
  },
  {
    "bvid": "BV1SZ421u7d5",
    "title": "【TF家族练习生】《星期五练习生》48：吵吵闹闹大挑战",
    "cover": "http://i2.hdslb.com/bfs/archive/6643b18733f77ed0fd6c7d5ed533f8ea27c05850.jpg",
    "url": "https://www.bilibili.com/video/BV1SZ421u7d5/",
    "date": "2024-06"
  },
  {
    "bvid": "BV1u142117JB",
    "title": "【TF家族练习生】《星期五练习生》47：六一儿童汇演（下）",
    "cover": "http://i0.hdslb.com/bfs/archive/b69afd069432a7799e61e4e2e60c98c0e9b7e063.jpg",
    "url": "https://www.bilibili.com/video/BV1u142117JB/",
    "date": "2024-06"
  },
  {
    "bvid": "BV1cn4y197Kj",
    "title": "【TF家族练习生】《星期五练习生》46：六一儿童汇演（上）",
    "cover": "http://i0.hdslb.com/bfs/archive/b69afd069432a7799e61e4e2e60c98c0e9b7e063.jpg",
    "url": "https://www.bilibili.com/video/BV1cn4y197Kj/",
    "date": "2024-06"
  },
  {
    "bvid": "BV1nw4m1D72Z",
    "title": "【TF家族练习生】《星期五练习生》45：去见师兄啦！",
    "cover": "http://i2.hdslb.com/bfs/archive/7c4f58f989ec07a54b21c11f4f77227591ef283a.jpg",
    "url": "https://www.bilibili.com/video/BV1nw4m1D72Z/",
    "date": "2024-05"
  },
  {
    "bvid": "BV17M4m1o7BG",
    "title": "【TF家族练习生】《星期五练习生》44：最受欢迎的你（下）",
    "cover": "http://i0.hdslb.com/bfs/archive/a98ba4469eed560a8a397d318d6a5a4e481ec1b0.jpg",
    "url": "https://www.bilibili.com/video/BV17M4m1o7BG/",
    "date": "2024-05"
  },
  {
    "bvid": "BV1az421D73v",
    "title": "【TF家族练习生】《星期五练习生》43：最受欢迎的你（上）",
    "cover": "http://i2.hdslb.com/bfs/archive/6978010a80bfbbb9818c4229db3d95f94562f832.jpg",
    "url": "https://www.bilibili.com/video/BV1az421D73v/",
    "date": "2024-05"
  },
  {
    "bvid": "BV1VD421J7zq",
    "title": "【TF家族练习生】《星期五练习生》42:「嘻游记」挖一条时空隧道",
    "cover": "http://i2.hdslb.com/bfs/archive/cbad28610774dc7bac366540e62ebcb0c15976c8.jpg",
    "url": "https://www.bilibili.com/video/BV1VD421J7zq/",
    "date": "2024-04"
  },
  {
    "bvid": "BV1Lp421R7TU",
    "title": "【TF家族练习生】《星期五练习生》41:「嘻游记」噼里啪啦 噼里啪啦",
    "cover": "http://i2.hdslb.com/bfs/archive/1072b412ad921a2bca7d0289499b4a516ce3f470.jpg",
    "url": "https://www.bilibili.com/video/BV1Lp421R7TU/",
    "date": "2024-04"
  },
  {
    "bvid": "BV1hx4y1Y7Xt",
    "title": "【TF家族练习生】《星期五练习生》40:「嘻游记」小鸡小鱼小猪和小莓",
    "cover": "http://i2.hdslb.com/bfs/archive/ad192442df43a493ed5ad53fb647fbe9ff6f9bc2.jpg",
    "url": "https://www.bilibili.com/video/BV1hx4y1Y7Xt/",
    "date": "2024-04"
  },
  {
    "bvid": "BV1Mq421P7xZ",
    "title": "【TF家族练习生】《星期五练习生》39:「嘻游记」今天晚上不睡觉",
    "cover": "http://i0.hdslb.com/bfs/archive/21c5630b30f2d11e6060d3c9744806255a8861b0.jpg",
    "url": "https://www.bilibili.com/video/BV1Mq421P7xZ/",
    "date": "2024-03"
  },
  {
    "bvid": "BV17j421d7LV",
    "title": "【TF家族练习生】《星期五练习生》38:「嘻游记」进村第一天",
    "cover": "http://i1.hdslb.com/bfs/archive/38a249a3827ca5d9a61dc315ea21687d80a25e78.jpg",
    "url": "https://www.bilibili.com/video/BV17j421d7LV/",
    "date": "2024-03"
  },
  {
    "bvid": "BV1kC411b7Ub",
    "title": "【TF家族练习生】《星期五练习生》37：我眼中的他",
    "cover": "http://i0.hdslb.com/bfs/archive/c62a999bfdafad8bd5e85f398d64936a37796c55.jpg",
    "url": "https://www.bilibili.com/video/BV1kC411b7Ub/",
    "date": "2024-03"
  },
  {
    "bvid": "BV1hF4m1M7ZT",
    "title": "【TF家族练习生】《星期五练习生》36：睡衣派对",
    "cover": "http://i2.hdslb.com/bfs/archive/d7568d77e2947df939de7a24857f2898efe835d0.jpg",
    "url": "https://www.bilibili.com/video/BV1hF4m1M7ZT/",
    "date": "2024-02"
  },
  {
    "bvid": "BV1Qu4m1P7Wx",
    "title": "【TF家族练习生】《星期五练习生》35番外：️是谁抢走了我的麦克风",
    "cover": "http://i2.hdslb.com/bfs/archive/d2d292806f912d866d62ef7f55cffbcb1dd8e2c8.jpg",
    "url": "https://www.bilibili.com/video/BV1Qu4m1P7Wx/",
    "date": "2024-02"
  },
  {
    "bvid": "BV1cz421d7K9",
    "title": "【TF家族练习生】《星期五练习生》35：新春茶话会（下）",
    "cover": "http://i2.hdslb.com/bfs/archive/d2d292806f912d866d62ef7f55cffbcb1dd8e2c8.jpg",
    "url": "https://www.bilibili.com/video/BV1cz421d7K9/",
    "date": "2024-02"
  },
  {
    "bvid": "BV1oz421R7k4",
    "title": "【TF家族练习生】《星期五练习生》34：新春茶话会（上）",
    "cover": "http://i2.hdslb.com/bfs/archive/d2d292806f912d866d62ef7f55cffbcb1dd8e2c8.jpg",
    "url": "https://www.bilibili.com/video/BV1oz421R7k4/",
    "date": "2024-02"
  },
  {
    "bvid": "BV1ig4y1U7TY",
    "title": "【TF家族练习生】《星期五练习生》33：游乐园竞赛",
    "cover": "http://i0.hdslb.com/bfs/archive/ef269627a377380dbb3b09d5a951906652b27bd9.jpg",
    "url": "https://www.bilibili.com/video/BV1ig4y1U7TY/",
    "date": "2024-01"
  },
  {
    "bvid": "BV1Mg4y1r73p",
    "title": "【TF家族练习生】《星期五练习生》32：下浩里美食地图（下）",
    "cover": "http://i0.hdslb.com/bfs/archive/c681230d7ca7fa82ff70efb137769a0f05c00b3e.jpg",
    "url": "https://www.bilibili.com/video/BV1Mg4y1r73p/",
    "date": "2023-12"
  },
  {
    "bvid": "BV1nQ4y137R6",
    "title": "【TF家族练习生】《星期五练习生》31：下浩里美食地图（中）",
    "cover": "http://i1.hdslb.com/bfs/archive/5ea6d57a66dcafa7548f8eee6c7c88c472ceb048.jpg",
    "url": "https://www.bilibili.com/video/BV1nQ4y137R6/",
    "date": "2023-12"
  },
  {
    "bvid": "BV1Qb4y1G79n",
    "title": "【TF家族练习生】《星期五练习生》30：下浩里美食地图（上）",
    "cover": "http://i0.hdslb.com/bfs/archive/3283d68dda66f8b38f8014c1e0c7dd248323eba2.jpg",
    "url": "https://www.bilibili.com/video/BV1Qb4y1G79n/",
    "date": "2023-12"
  },
  {
    "bvid": "BV1Yj411j7YS",
    "title": "【TF家族练习生】《星期五练习生》29：冬日养生大作战",
    "cover": "http://i0.hdslb.com/bfs/archive/53da94518a9eeda061b4f406ecacfb148e1239fb.jpg",
    "url": "https://www.bilibili.com/video/BV1Yj411j7YS/",
    "date": "2023-12"
  },
  {
    "bvid": "BV1jw411K7dB",
    "title": "【TF家族练习生】《星期五练习生》28：决战吧！反射神经",
    "cover": "http://i0.hdslb.com/bfs/archive/778a090dd86255b17b5acde852b246943a4bf143.jpg",
    "url": "https://www.bilibili.com/video/BV1jw411K7dB/",
    "date": "2023-11"
  },
  {
    "bvid": "BV17u4y1N79D",
    "title": "【TF家族练习生】《星期五练习生》27：爱的抱抱",
    "cover": "http://i2.hdslb.com/bfs/archive/ad37f4331c95c43c9408224e0614f30792169f15.jpg",
    "url": "https://www.bilibili.com/video/BV17u4y1N79D/",
    "date": "2023-11"
  },
  {
    "bvid": "BV1Mu4y177Jn",
    "title": "【TF家族练习生】《星期五练习生》26：秋结野营会（下）",
    "cover": "http://i0.hdslb.com/bfs/archive/170c591b426ebf6c743cbbaa8de629578234f607.jpg",
    "url": "https://www.bilibili.com/video/BV1Mu4y177Jn/",
    "date": "2023-11"
  },
  {
    "bvid": "BV1VG411C7ux",
    "title": "【TF家族练习生】《星期五练习生》25：秋结野营会（上）",
    "cover": "http://i1.hdslb.com/bfs/archive/f349d067d405edde17d6e544ec74f7113adef051.jpg",
    "url": "https://www.bilibili.com/video/BV1VG411C7ux/",
    "date": "2023-10"
  },
  {
    "bvid": "BV1Bw411B7Zf",
    "title": "【TF家族练习生】《星期五练习生》24：突破极限的柔韧竞赛",
    "cover": "http://i2.hdslb.com/bfs/archive/bf5b08e21923c0d8cfb8622265aba1b799aa35b7.jpg",
    "url": "https://www.bilibili.com/video/BV1Bw411B7Zf/",
    "date": "2023-10"
  },
  {
    "bvid": "BV1Pw41167hv",
    "title": "【TF家族练习生】《星期五练习生》23：间谍游戏",
    "cover": "http://i1.hdslb.com/bfs/archive/40044be29604056b6f563532b413563ecc3a3652.jpg",
    "url": "https://www.bilibili.com/video/BV1Pw41167hv/",
    "date": "2023-10"
  },
  {
    "bvid": "BV1YG411m7M3",
    "title": "【TF家族练习生】《星期五练习生》22：南国客栈诡事录（下）",
    "cover": "http://i2.hdslb.com/bfs/archive/4ef409950be36833ee802962751c5b513d1d57e4.jpg",
    "url": "https://www.bilibili.com/video/BV1YG411m7M3/",
    "date": "2023-10"
  },
  {
    "bvid": "BV1Lp4y1c7ag",
    "title": "【TF家族练习生】《星期五练习生》21：南国客栈诡事录（上）",
    "cover": "http://i1.hdslb.com/bfs/archive/08591301873e17648a7f9076beec9a114c0b34ad.jpg",
    "url": "https://www.bilibili.com/video/BV1Lp4y1c7ag/",
    "date": "2023-09"
  },
  {
    "bvid": "BV1vw411v7db",
    "title": "【TF家族练习生】《星期五练习生》20：oooooo的你",
    "cover": "http://i1.hdslb.com/bfs/archive/f92fb0c7b01bce58d36005dd08b493f5e7830535.jpg",
    "url": "https://www.bilibili.com/video/BV1vw411v7db/",
    "date": "2023-09"
  },
  {
    "bvid": "BV1bk4y1w736",
    "title": "【TF家族练习生】《星期五练习生》19：合宿特辑——是and不是end（下）",
    "cover": "http://i1.hdslb.com/bfs/archive/c4734b8bcfba1e1cf86e2c01d7afed715e39031d.jpg",
    "url": "https://www.bilibili.com/video/BV1bk4y1w736/",
    "date": "2023-09"
  },
  {
    "bvid": "BV1hP41187a3",
    "title": "【TF家族练习生】《星期五练习生》18：合宿特辑——是and不是end（上）",
    "cover": "http://i2.hdslb.com/bfs/archive/224bbd6d5a832d865e3aad8ded005bf4632f132b.jpg",
    "url": "https://www.bilibili.com/video/BV1hP41187a3/",
    "date": "2023-09"
  },
  {
    "bvid": "BV1dp4y177A4",
    "title": "【TF家族练习生】《星期五练习生》17：飞翔体验券",
    "cover": "http://i0.hdslb.com/bfs/archive/951efe3644e63aafda1f3fd1692aaef0e427eda8.jpg",
    "url": "https://www.bilibili.com/video/BV1dp4y177A4/",
    "date": "2023-08"
  },
  {
    "bvid": "BV1Uj411B72U",
    "title": "【TF家族练习生】《星期五练习生》16：我们去北京啦！",
    "cover": "http://i1.hdslb.com/bfs/archive/8c071dcdb1864428add1451184b507a6deeaf51b.jpg",
    "url": "https://www.bilibili.com/video/BV1Uj411B72U/",
    "date": "2023-08"
  },
  {
    "bvid": "BV1ZV4y147ph",
    "title": "【TF家族练习生】《星期五练习生》14：清凉一\"吓\"之「消失的他」",
    "cover": "http://i1.hdslb.com/bfs/archive/815cc9f9aa9adff60a85768861f41b6fa50adefa.jpg",
    "url": "https://www.bilibili.com/video/BV1ZV4y147ph/",
    "date": "2023-07"
  },
  {
    "bvid": "BV1LW4y1Z74h",
    "title": "【TF家族练习生】《星期五练习生》13：甜“秘密”的任务",
    "cover": "http://i2.hdslb.com/bfs/archive/563433b6fac101dcac72b136ff5365d7258211f7.jpg",
    "url": "https://www.bilibili.com/video/BV1LW4y1Z74h/",
    "date": "2023-07"
  },
  {
    "bvid": "BV1Eu411j7mp",
    "title": "【TF家族练习生】《星期五练习生》12：绿色暴汗之旅",
    "cover": "http://i2.hdslb.com/bfs/archive/91ff722dce108d918192d5facab2e3cdb8edb90a.jpg",
    "url": "https://www.bilibili.com/video/BV1Eu411j7mp/",
    "date": "2023-07"
  },
  {
    "bvid": "BV1Nc411u7iB",
    "title": "【TF家族练习生】《星期五练习生》11：端午节特辑",
    "cover": "http://i0.hdslb.com/bfs/archive/978447ae5aa43636beb30b5958603e2772eef3aa.jpg",
    "url": "https://www.bilibili.com/video/BV1Nc411u7iB/",
    "date": "2023-06"
  },
  {
    "bvid": "BV16W4y1S7QS",
    "title": "【TF家族练习生】《星期五练习生》09番外：一个惬意的午后",
    "cover": "http://i1.hdslb.com/bfs/archive/7404fe360ed9f6b755070fdbda4f5c78200e0168.jpg",
    "url": "https://www.bilibili.com/video/BV16W4y1S7QS/",
    "date": "2023-06"
  },
  {
    "bvid": "BV1mo4y1N7SX",
    "title": "【TF家族练习生】《星期五练习生》10：谁是“伪装者”？",
    "cover": "http://i1.hdslb.com/bfs/archive/865417e5ff8583b7e7dfe7d05f131de37e23a31b.jpg",
    "url": "https://www.bilibili.com/video/BV1mo4y1N7SX/",
    "date": "2023-06"
  },
  {
    "bvid": "BV1iL411i7MR",
    "title": "【TF家族练习生】《星期五练习生》09：幼儿园一日助教体验",
    "cover": "http://i1.hdslb.com/bfs/archive/1f8457af58e39df497f0c960d11f91ca21d5e071.jpg",
    "url": "https://www.bilibili.com/video/BV1iL411i7MR/",
    "date": "2023-06"
  },
  {
    "bvid": "BV1PV4y1U7Xt",
    "title": "【TF家族练习生】《星期五练习生》08：儿童带儿童过儿童节",
    "cover": "http://i2.hdslb.com/bfs/archive/d3cfa0d79e916e12403a26e76450fc1f41040424.jpg",
    "url": "https://www.bilibili.com/video/BV1PV4y1U7Xt/",
    "date": "2023-06"
  },
  {
    "bvid": "BV1fu411s7cW",
    "title": "【TF家族练习生】《星期五练习生》07番外：TFBA篮球赛",
    "cover": "http://i0.hdslb.com/bfs/archive/46f33c629ddbc4edf6c68f83e6636da62aad46ac.jpg",
    "url": "https://www.bilibili.com/video/BV1fu411s7cW/",
    "date": "2023-05"
  },
  {
    "bvid": "BV1cu411s7tX",
    "title": "【TF家族练习生】《星期五练习生》07：同学，可以和你做同桌吗？",
    "cover": "http://i0.hdslb.com/bfs/archive/eec7acc4f67372d8bb1a706ef81cfede9be2435a.jpg",
    "url": "https://www.bilibili.com/video/BV1cu411s7tX/",
    "date": "2023-05"
  },
  {
    "bvid": "BV1hc411N77w",
    "title": "【TF家族练习生】《星期五练习生》06：春结野营会之难忘的春游",
    "cover": "http://i2.hdslb.com/bfs/archive/15659739a12f2937acaa5699c03f712595c0a0ec.jpg",
    "url": "https://www.bilibili.com/video/BV1hc411N77w/",
    "date": "2023-05"
  },
  {
    "bvid": "BV1Km4y1C7n6",
    "title": "【TF家族练习生】《星期五练习生》05：春结野营会之「春结晚会」",
    "cover": "http://i1.hdslb.com/bfs/archive/e51f2446239d15caec67fcb9b0f15382661d21c7.jpg",
    "url": "https://www.bilibili.com/video/BV1Km4y1C7n6/",
    "date": "2023-04"
  },
  {
    "bvid": "BV1DT411n7XP",
    "title": "【TF家族练习生】《星期五练习生》04：今天是去看演唱会的日子！",
    "cover": "http://i1.hdslb.com/bfs/archive/ce74b07c1e3d782648d90b2f4e0613fb4a8ea0dc.jpg",
    "url": "https://www.bilibili.com/video/BV1DT411n7XP/",
    "date": "2023-04"
  },
  {
    "bvid": "BV1r54y1F7Mi",
    "title": "【TF家族练习生】《星期五练习生》03：公式照拍摄现场花絮",
    "cover": "http://i1.hdslb.com/bfs/archive/ce74b07c1e3d782648d90b2f4e0613fb4a8ea0dc.jpg",
    "url": "https://www.bilibili.com/video/BV1r54y1F7Mi/",
    "date": "2023-04"
  },
  {
    "bvid": "BV12L411U7H7",
    "title": "【TF家族练习生】《星期五练习生》02：嘿，一起来创建我的「个性标签」！",
    "cover": "http://i1.hdslb.com/bfs/archive/a7fbe12c23432f17e100065948326cd5e9e5fbdf.jpg",
    "url": "https://www.bilibili.com/video/BV12L411U7H7/",
    "date": "2023-04"
  },
  {
    "bvid": "BV1Tg4y1G7kG",
    "title": "【TF家族练习生】《星期五练习生》01：人生的第一份简历",
    "cover": "http://i0.hdslb.com/bfs/archive/164a5945077c019e5101671b57b78c6aba972a00.jpg",
    "url": "https://www.bilibili.com/video/BV1Tg4y1G7kG/",
    "date": "2023-03"
  }
]